pymorphous
settings
run_examples
run_pymorphous
make_gource
extensions
examples
make_video
