Metadata-Version: 1.0
Name: pymorphous
Version: 0.1.0
Summary: Spatial computing library and simulator for Python
Home-page: http://www.pymorphous.org/
Author: Charles Dietrich
Author-email: charles.m.dietrich at gmail
License: UNKNOWN
Keywords: spatial_computing,amorphous_computing,simulator,robotics
Platform: UNKNOWN
Classifier: Programming Language :: Python
Classifier: Development Status :: 3 - Alpha
Classifier: Intended Audience :: Developers
Classifier: License :: OSI Approved
Classifier: Operating System :: OS Independent
Classifier: Topic :: Software Development :: Libraries :: Python Modules
Classifier: Topic :: Scientific/Engineering
Classifier: Topic :: Multimedia :: Graphics
